odoo8_addon_supplier_inventory_import_ubl-8.0.1.2.0-nspkg.pth
odoo_addons/supplier_inventory_import_ubl/README.rst
odoo_addons/supplier_inventory_import_ubl/__init__.py
odoo_addons/supplier_inventory_import_ubl/__openerp__.py
odoo_addons/supplier_inventory_import_ubl/demo/partner.xml
odoo_addons/supplier_inventory_import_ubl/demo/product.xml
odoo_addons/supplier_inventory_import_ubl/i18n/supplier_inventory_import_ubl.pot
odoo_addons/supplier_inventory_import_ubl/models/__init__.py
odoo_addons/supplier_inventory_import_ubl/models/company.py
odoo_addons/supplier_inventory_import_ubl/models/product.py
odoo_addons/supplier_inventory_import_ubl/models/stock.py
odoo_addons/supplier_inventory_import_ubl/models/supplierinfo.py
odoo_addons/supplier_inventory_import_ubl/readme/CONFIGURE.rst
odoo_addons/supplier_inventory_import_ubl/readme/CONTRIBUTORS.rst
odoo_addons/supplier_inventory_import_ubl/readme/CREDITS.rst
odoo_addons/supplier_inventory_import_ubl/readme/DESCRIPTION.rst
odoo_addons/supplier_inventory_import_ubl/readme/ROADMAP.rst
odoo_addons/supplier_inventory_import_ubl/readme/USAGE.rst
odoo_addons/supplier_inventory_import_ubl/static/description/icon.png
odoo_addons/supplier_inventory_import_ubl/static/description/import.png
odoo_addons/supplier_inventory_import_ubl/static/description/index.html
odoo_addons/supplier_inventory_import_ubl/static/description/product.png
odoo_addons/supplier_inventory_import_ubl/static/description/settings.png
odoo_addons/supplier_inventory_import_ubl/static/description/stock_report.png
odoo_addons/supplier_inventory_import_ubl/static/description/supplier_info.png
odoo_addons/supplier_inventory_import_ubl/static/description/supplierinfo_updated_data.png
odoo_addons/supplier_inventory_import_ubl/static/description/wood_message.png
odoo_addons/supplier_inventory_import_ubl/tests/__init__.py
odoo_addons/supplier_inventory_import_ubl/tests/test_import.py
odoo_addons/supplier_inventory_import_ubl/tests/inventory_report_sample/main.xml
odoo8_addon_supplier_inventory_import_ubl-8.0.1.2.0.dist-info/METADATA
odoo8_addon_supplier_inventory_import_ubl-8.0.1.2.0.dist-info/WHEEL
odoo8_addon_supplier_inventory_import_ubl-8.0.1.2.0.dist-info/namespace_packages.txt
odoo8_addon_supplier_inventory_import_ubl-8.0.1.2.0.dist-info/top_level.txt
odoo8_addon_supplier_inventory_import_ubl-8.0.1.2.0.dist-info/RECORD
